MANIFEST.in
setup.py
admin_export/__init__.py
admin_export/admin.py
admin_export/models.py
admin_export/urls.py
admin_export/views.py
admin_export/templates/admin_export/export_to_xls.html
admin_export/templates/admin_export/fields.html
django_admin_export.egg-info/PKG-INFO
django_admin_export.egg-info/SOURCES.txt
django_admin_export.egg-info/dependency_links.txt
django_admin_export.egg-info/requires.txt
django_admin_export.egg-info/top_level.txt