Metadata-Version: 1.1
Name: django-admin-export
Version: 2.0
Summary: Generic export to xls action for Django admin interface
Home-page: https://github.com/burke-software/django-admin-export
Author: David Burke
Author-email: david@burkesoftware.com
License: BSD
Keywords: django admin
Platform: UNKNOWN
Classifier: Development Status :: 4 - Beta
Classifier: Environment :: Web Environment
Classifier: Framework :: Django
Classifier: Programming Language :: Python
Classifier: Intended Audience :: Developers
Classifier: Intended Audience :: System Administrators
Classifier: License :: OSI Approved :: BSD License
